LICENSE
README.md
pyproject.toml
setup.py
./hygese/__init__.py
./hygese/hygese.py
./hygese/libhgscvrp.dylib
./hygese/tests/__init__.py
./hygese/tests/test_cvrp.py
./hygese/tests/test_tsp.py
hygese.egg-info/PKG-INFO
hygese.egg-info/SOURCES.txt
hygese.egg-info/dependency_links.txt
hygese.egg-info/requires.txt
hygese.egg-info/top_level.txt