Metadata-Version: 2.1
Name: hygese
Version: 0.0.0.7
Summary: A Python wrapper for the HGS-CVRP solver
Home-page: https://github.com/chkwon/PyHygese
Author: Changhyun Kwon
Author-email: chkwon@gmail.com
License: UNKNOWN
Project-URL: Bug Tracker, https://github.com/chkwon/PyHygese/issues
Platform: UNKNOWN
Classifier: Programming Language :: Python :: 3
Classifier: License :: OSI Approved :: MIT License
Classifier: Operating System :: OS Independent
Requires-Python: >=3.6
License-File: LICENSE
